LICENSE
MANIFEST.in
README.rst
setup.cfg
setup.py
versioneer.py
tests/__init__.py
tests/test_general.py
tpRigToolkit/__init__.py
tpRigToolkit/libs/__init__.py
tpRigToolkit/libs/controlrig/__init__.py
tpRigToolkit/libs/controlrig/__logging__.ini
tpRigToolkit/libs/controlrig/__version__.py
tpRigToolkit/libs/controlrig/_version.py
tpRigToolkit/libs/controlrig/data.json
tpRigToolkit/libs/controlrig/core/__init__.py
tpRigToolkit/libs/controlrig/core/consts.py
tpRigToolkit/libs/controlrig/core/control.py
tpRigToolkit/libs/controlrig/core/controllib.py
tpRigToolkit/libs/controlrig/dccs/__init__.py
tpRigToolkit/libs/controlrig/dccs/max/__init__.py
tpRigToolkit/libs/controlrig/dccs/max/controllib.py
tpRigToolkit/libs/controlrig/dccs/maya/__init__.py
tpRigToolkit/libs/controlrig/dccs/maya/controllib.py
tpRigToolkit/libs/controlrig/dccs/maya/controlutils.py
tpRigToolkit_libs_controlrig.egg-info/PKG-INFO
tpRigToolkit_libs_controlrig.egg-info/SOURCES.txt
tpRigToolkit_libs_controlrig.egg-info/dependency_links.txt
tpRigToolkit_libs_controlrig.egg-info/not-zip-safe
tpRigToolkit_libs_controlrig.egg-info/requires.txt
tpRigToolkit_libs_controlrig.egg-info/top_level.txt