Metadata-Version: 2.1
Name: tpRigToolkit-libs-controlrig
Version: 0.0.2
Summary: Library to manage controls for rigs
Home-page: https://github.com/tpRigToolkit/tpRigToolkit-libs-controlrig
Author: Tomas Poveda
Author-email: tpovedatd@gmail.com
License: MIT
Platform: UNKNOWN
Provides-Extra: dev
Provides-Extra: test
